custom_plotly_templates/__init__.py
custom_plotly_templates/_version.py
custom_plotly_templates/render_config.py
custom_plotly_templates/templates/__init__.py
custom_plotly_templates/templates/white.py
custom_plotly_templates-2.0.1.dist-info/LICENSE
custom_plotly_templates-2.0.1.dist-info/METADATA
custom_plotly_templates-2.0.1.dist-info/WHEEL
custom_plotly_templates-2.0.1.dist-info/RECORD
