Metadata-Version: 2.1
Name: custom-plotly-templates
Version: 2.0.1
Summary: Custom templates and configurations for Plotly
Home-page: https://github.com/rusmux/custom-plotly-templates
License: MIT
Keywords: plotly,template,config
Author: Ruslan Mukhametshin
Author-email: rusmux21@gmail.com
Requires-Python: >=3.8,<3.11
Classifier: License :: OSI Approved :: MIT License
Classifier: Programming Language :: Python :: 3
Classifier: Programming Language :: Python :: 3.8
Classifier: Programming Language :: Python :: 3.9
Classifier: Programming Language :: Python :: 3.10
Requires-Dist: plotly (>=5.14.1)
